[
  {
    "id": 1,
    "title": "Microsoft",
    "description": "Microsoft Surface Laptop Go 10th Gen Intel Core™ i5-1035G1 12.4 inch Touchscreen Laptop (8GB/128GB SSD/Windows 10 Home in S Mode/Intel UHD Graphics/Platinum/1.110 kg), THH-00023",
    "price": "42,999",
    "image": "https://images-eu.ssl-images-amazon.com/images/G/31/img20/Laptops/Microsoft/Surafece_GO/Untitled-2.jpg"
  },
  {
    "id": 2,
    "title": "JBL",
    "description": "The best just got got better Rockerz 255+ pro plus upto 40 hours non stop playback(IPx7 water and sweat resistance)",
    "price": "2,999",
    "image": "https://images-eu.ssl-images-amazon.com/images/G/31/img21/Audio/JBL/c115/updated/R03_JBL_Gw_670x645.jpg"
  },
  {
    "id": 3,
    "title": "Visit the Alcatel Store",
    "description": "Alcatel TKEE MAX Tablet with Google Voice Assistant (10.1inch, 2GB+32GB, Wi-Fi only, Android 10, Type C Charging), Mint Green",
    "price": "9,999",
    "image": "https://images-eu.ssl-images-amazon.com/images/G/31/img19/2020/PC/Storage/September/New/alcatel_Max_670x645-electronicpage-290121.jpg"
  },
  {
    "id": 4,
    "title": "JBL",
    "description": "JBL Commercial CSLM20 Omnidirectional Lavalier Microphone, Earphone for calls, Video Conferences, and Monitoring",
    "price": "949",
    "image": "https://images-eu.ssl-images-amazon.com/images/G/31/img21/MusicalInstruments/Hero/R01/670x645_jbl.jpg"
  },
  {
    "id": 5,
    "title": "Mi",
    "description": "Alcatel TKEE MAX Tablet with Google Voice Assistant (10.1inch, 2GB+32GB, Wi-Fi only, Android 10, Type C Charging), Mint Green",
    "price": "2,499",
    "image": "https://images-eu.ssl-images-amazon.com/images/G/31/img20/CEPC/Wearables/Mi/Band5/Refresh/Mi-Band-5_670x645.jpg"
  },
  {
    "id": 6,
    "title": "Boat",
    "description": "Alcatel TKEE MAX Tablet with Google Voice Assistant (10.1inch, 2GB+32GB, Wi-Fi only, Android 10, Type C Charging), Mint Green",
    "price": "2,299",
    "image": "https://images-eu.ssl-images-amazon.com/images/G/31/img21/Audio/unrec1499/Boat_Gw_670x6454.jpg"
  },
  {
    "id": 7,
    "title": "Noise",
    "description": "Alcatel TKEE MAX Tablet with Google Voice Assistant (10.1inch, 2GB+32GB, Wi-Fi only, Android 10, Type C Charging), Mint Green",
    "price": "7,999",
    "image": "https://images-eu.ssl-images-amazon.com/images/G/31/img20/CEPC/Wearables/Noise/ColorfitPro3/Ingress/LaunchDate/Coloerfit_Pro_3_670x645.jpg"
  },
  {
    "id": 8,
    "title": "UltraGear",
    "description": "Alcatel TKEE MAX Tablet with Google Voice Assistant (10.1inch, 2GB+32GB, Wi-Fi only, Android 10, Type C Charging), Mint Green",
    "price": "9,279",
    "image": "https://images-eu.ssl-images-amazon.com/images/G/31/img20/Monitors/LG/Hero_Banner_27GN950-670x645.jpg"
  },
  {
    "id": 9,
    "title": "Mi NoteBook",
    "description": "Alcatel TKEE MAX Tablet with Google Voice Assistant (10.1inch, 2GB+32GB, Wi-Fi only, Android 10, Type C Charging), Mint Green",
    "price": "7,999",
    "image": "https://images-eu.ssl-images-amazon.com/images/G/31/img20/Laptops/MI_Laptops/2021/Mi_I3_Coming_Soon/Shop_Now/P43248868_IN_PC_Mi-notebook-Jan_2021_670x645_V2.jpg"
  },
  {
    "id": 10,
    "title": "Noise",
    "description": "Alcatel TKEE MAX Tablet with Google Voice Assistant (10.1inch, 2GB+32GB, Wi-Fi only, Android 10, Type C Charging), Mint Green",
    "price": "2,999",
    "image": "https://images-eu.ssl-images-amazon.com/images/G/31/img20/Audio/JBL_C115TWS/22/elan.jpeg"
  },
  {
    "id": 11,
    "title": "Visit the Alcatel Store",
    "description": "Alcatel TKEE MAX Tablet with Google Voice Assistant (10.1inch, 2GB+32GB, Wi-Fi only, Android 10, Type C Charging), Mint Green",
    "price": "16,999",
    "image": "https://images-eu.ssl-images-amazon.com/images/G/31/img20/PC/Networking/Category/ingress_lagfree_670x640.gif"
  },
  {
    "id": 12,
    "title": "Visit the Alcatel Store",
    "description": "Alcatel TKEE MAX Tablet with Google Voice Assistant (10.1inch, 2GB+32GB, Wi-Fi only, Android 10, Type C Charging), Mint Green",
    "price": "9,999",
    "image": "https://images-eu.ssl-images-amazon.com/images/G/31/img21/MusicalInstruments/Electronics/670x645_stringed_instruments.jpg"
  },
  {
    "id": 13,
    "title": "Visit the Alcatel Store",
    "description": "Alcatel TKEE MAX Tablet with Google Voice Assistant (10.1inch, 2GB+32GB, Wi-Fi only, Android 10, Type C Charging), Mint Green",
    "price": "4,999",
    "image": "https://images-eu.ssl-images-amazon.com/images/G/31/img20/PC/Accessories/PC_acc_WFH_670x645.jpg"
  },
  {
    "id": 14,
    "title": "Visit the Alcatel Store",
    "description": "Alcatel TKEE MAX Tablet with Google Voice Assistant (10.1inch, 2GB+32GB, Wi-Fi only, Android 10, Type C Charging), Mint Green",
    "price": "9,799",
    "image": "https://images-eu.ssl-images-amazon.com/images/G/31/img21/Audio/skullcandy/Skullcandy_Gw_670x645.jpg"
  },
  {
    "id": 15,
    "title": "Visit the Alcatel Store",
    "description": "Alcatel TKEE MAX Tablet with Google Voice Assistant (10.1inch, 2GB+32GB, Wi-Fi only, Android 10, Type C Charging), Mint Green",
    "price": "5,699",
    "image": "https://images-eu.ssl-images-amazon.com/images/G/31/img20/OP/SFH/D15593517_IN_OP_BTS_Mar20_670x645.jpg"
  },
  {
    "id": 16,
    "title": "Visit the Alcatel Store",
    "description": "Alcatel TKEE MAX Tablet with Google Voice Assistant (10.1inch, 2GB+32GB, Wi-Fi only, Android 10, Type C Charging), Mint Green",
    "price": "7,969",
    "image": "https://images-eu.ssl-images-amazon.com/images/G/31/img21/MusicalInstruments/Casio/CT-S_Series_670x645.jpg"
  },
  {
    "id": 17,
    "title": "Visit the Alcatel Store",
    "description": "Alcatel TKEE MAX Tablet with Google Voice Assistant (10.1inch, 2GB+32GB, Wi-Fi only, Android 10, Type C Charging), Mint Green",
    "price": "9,799",
    "image": "https://images-eu.ssl-images-amazon.com/images/G/31/img20/Laptops/MI_Laptops/2021/Revised_Prices/Mi_NoteBook_Sale_Banners_675x645.jpg"
  },
  {
    "id": 18,
    "title": "Visit the Alcatel Store",
    "description": "Alcatel TKEE MAX Tablet with Google Voice Assistant (10.1inch, 2GB+32GB, Wi-Fi only, Android 10, Type C Charging), Mint Green",
    "price": "9,099",
    "image": "https://images-eu.ssl-images-amazon.com/images/G/31/img20/Audio/Newlaunches/Hdpns_Gw_1_670x645.jpg"
  },
  {
    "id": 19,
    "title": "Visit the Alcatel Store",
    "description": "Alcatel TKEE MAX Tablet with Google Voice Assistant (10.1inch, 2GB+32GB, Wi-Fi only, Android 10, Type C Charging), Mint Green",
    "price": "9,959",
    "image": "https://images-eu.ssl-images-amazon.com/images/G/31/img20/TVs/BAU/Hisense58/670x645_1.jpg"
  },
  {
    "id": 20,
    "title": "Visit the Alcatel Store",
    "description": "Alcatel TKEE MAX Tablet with Google Voice Assistant (10.1inch, 2GB+32GB, Wi-Fi only, Android 10, Type C Charging), Mint Green",
    "price": "8,999",
    "image": "https://images-eu.ssl-images-amazon.com/images/G/31/img21/Cameras/670x645_nano_drone.jpg"
  },
  {
    "id": 21,
    "title": "Visit the Alcatel Store",
    "description": "Alcatel TKEE MAX Tablet with Google Voice Assistant (10.1inch, 2GB+32GB, Wi-Fi only, Android 10, Type C Charging), Mint Green",
    "price": "12,999",
    "image": "https://images-eu.ssl-images-amazon.com/images/G/31/img21/Audio/coop/Audio-_670x645.jpg"
  },
  {
    "id": 22,
    "title": "Casio",
    "description": "Alcatel TKEE MAX Tablet with Google Voice Assistant (10.1inch, 2GB+32GB, Wi-Fi only, Android 10, Type C Charging), Mint Green",
    "price": "6,999",
    "image": "https://images-eu.ssl-images-amazon.com/images/G/31/img20/Audio/Newlaunches/Spkrs_Gw_670x645.jpg"
  },
  {
    "id": 23,
    "title": "LG",
    "description": "Alcatel TKEE MAX Tablet with Google Voice Assistant (10.1inch, 2GB+32GB, Wi-Fi only, Android 10, Type C Charging), Mint Green",
    "price": "22,999",
    "image": "https://images-eu.ssl-images-amazon.com/images/G/31/img20/Monitors/home-office_670x645.jpg"
  },
  {
    "id": 24,
    "title": "Visit the Alcatel Store",
    "description": "Alcatel TKEE MAX Tablet with Google Voice Assistant (10.1inch, 2GB+32GB, Wi-Fi only, Android 10, Type C Charging), Mint Green",
    "price": "40,999",
    "image": "https://images-eu.ssl-images-amazon.com/images/G/31/img20/PC/Accessories/Accessorize-your-Tablets_670x645.jpg"
  },
  {
    "id": 25,
    "title": "Sony",
    "description": "Alcatel TKEE MAX Tablet with Google Voice Assistant (10.1inch, 2GB+32GB, Wi-Fi only, Android 10, Type C Charging), Mint Green",
    "price": "52,999",
    "image": "https://images-eu.ssl-images-amazon.com/images/G/31/img20/Camera/670x645_camera_R01.jpg"
  },
  {
    "id": 26,
    "title": "Mi",
    "description": "Alcatel TKEE MAX Tablet with Google Voice Assistant (10.1inch, 2GB+32GB, Wi-Fi only, Android 10, Type C Charging), Mint Green",
    "price": "11,999",
    "image": "https://images-eu.ssl-images-amazon.com/images/G/31/img20/TVs/BAU/winterstore/D20179250_IN_HETV_Mi40_launch_670x645.jpg"
  }

]